ddfem/__init__.py
ddfem/__main__.py
ddfem/boundary.py
ddfem/model2ufl.py
ddfem/plot.py
ddfem/data/generate.py
ddfem/data/2.11.dev20250709/adapt_010e1455a389aa01992af42c0a3f4b14.cc
ddfem/data/2.11.dev20250709/boundary.modules
ddfem/data/2.11.dev20250709/femscheme_ddd4458a70dff1f9762ec5a96ca4ba9c.cc
ddfem/data/2.11.dev20250709/femscheme_f2a3cb32a864b08c0236366e732fb908.cc
ddfem/data/2.11.dev20250709/femspace_4ff9049b6f297245e5d33296d14cd684_d5b136dbe3c5077b69c99b8c322eb563.cc
ddfem/data/2.11.dev20250709/femspace_90f0a9524a8cb701e8ee5027b7658a0e_0faf32f13b591f4f60f83c591507b9be.cc
ddfem/data/2.11.dev20250709/geometry.modules
ddfem/data/2.11.dev20250709/hierarchicalgrid_472c2c2d007bf5604887ab2f16b7eb13.cc
ddfem/data/2.11.dev20250709/hierarchicalgrid_966e2a5c8356c5b278ccd3acad180f0a.cc
ddfem/data/2.11.dev20250709/hierarchicalgrid_d827e80243feae36e8b9006bb24207e7.cc
ddfem/data/2.11.dev20250709/indexset_e9c0cdc96a4fc702a0969c29910954e6.cc
ddfem/data/2.11.dev20250709/integrands_008eefa148b772fa3192dd3c1728c140v1_3_a524c1196983e65de1c06d7d6afdeb44.cc
ddfem/data/2.11.dev20250709/integrands_00ee9b3b89e4e44212e5b7ad7948a24ev1_3_a524c1196983e65de1c06d7d6afdeb44.cc
ddfem/data/2.11.dev20250709/integrands_2e6d4e3b5cff269867d26022ac7cee09v1_3_a524c1196983e65de1c06d7d6afdeb44.cc
ddfem/data/2.11.dev20250709/integrands_3bde0abfafcf45a3cff4d1029568ab5cv1_3_a524c1196983e65de1c06d7d6afdeb44.cc
ddfem/data/2.11.dev20250709/integrands_59ef814e4fbd86ef9c0aeac61e84e9a7v1_3_a524c1196983e65de1c06d7d6afdeb44.cc
ddfem/data/2.11.dev20250709/integrands_96ea175da69be26acf1a8d94dc0b3c93v1_3_a524c1196983e65de1c06d7d6afdeb44.cc
ddfem/data/2.11.dev20250709/integrands_bf510277401791ad5e30831b49a8ed7cv1_3_a524c1196983e65de1c06d7d6afdeb44.cc
ddfem/data/2.11.dev20250709/integrands_ed7208bd651abb351e34c9990e0313bcv1_3_a524c1196983e65de1c06d7d6afdeb44.cc
ddfem/data/2.11.dev20250709/intro.modules
ddfem/data/2.11.dev20250709/localfunction_00f2e5593eeb23f01906255d67244f6e_a524c1196983e65de1c06d7d6afdeb44.cc
ddfem-1.0.10.dist-info/licenses/LICENSE
ddfem-1.0.10.dist-info/METADATA
ddfem-1.0.10.dist-info/WHEEL
ddfem-1.0.10.dist-info/top_level.txt
ddfem-1.0.10.dist-info/RECORD
