Metadata-Version: 2.4
Name: ddfem
Version: 1.0.10
Summary: Diffuse domain finite element solver
Author-email: Luke Benfield <luke.benfield@warwick.ac.uk>, Andreas Dedner <a.s.dedner@warwick.ac.uk>
License-Expression: MIT
Project-URL: Homepage, https://gitlab.dune-project.org/dune-fem/ddfem
Project-URL: Issues, https://gitlab.dune-project.org/dune-fem/ddfem/-/issues
Project-URL: Documentation, https://ddfem.readthedocs.io/en/latest/index.html
Project-URL: Repository, https://gitlab.dune-project.org/dune-fem/ddfem.git
Classifier: Programming Language :: Python :: 3
Classifier: Operating System :: OS Independent
Requires-Python: >=3.9
License-File: LICENSE
Requires-Dist: fenics-ufl==2022.2.0
Requires-Dist: numpy
Requires-Dist: setuptools<79.1
Provides-Extra: dune
Requires-Dist: dune-fem==2.11.dev20250709; extra == "dune"
Requires-Dist: dune_alugrid==2.11.dev20250709; extra == "dune"
Requires-Dist: dune_common==2.11.dev20250709; extra == "dune"
Requires-Dist: dune_fem-dg==2.11.dev20250709; extra == "dune"
Requires-Dist: dune_geometry==2.11.dev20250709; extra == "dune"
Requires-Dist: dune_grid==2.11.dev20250709; extra == "dune"
Requires-Dist: dune_istl==2.11.dev20250709; extra == "dune"
Requires-Dist: dune_localfunctions==2.11.dev20250709; extra == "dune"
Requires-Dist: pygmsh; extra == "dune"
Provides-Extra: doc
Requires-Dist: jupyter; extra == "doc"
Requires-Dist: jupytext; extra == "doc"
Requires-Dist: nbsphinx; extra == "doc"
Requires-Dist: sphinx_rtd_theme; extra == "doc"
Requires-Dist: twine; extra == "doc"
Requires-Dist: build; extra == "doc"
Provides-Extra: dev
Requires-Dist: ddfem[doc,dune]; extra == "dev"
Dynamic: license-file
